passphera_core/__init__.py
passphera_core/entities.py
passphera_core/exceptions.py
passphera_core/utilities.py
passphera_core-0.34.0.dist-info/licenses/LICENSE
passphera_core-0.34.0.dist-info/METADATA
passphera_core-0.34.0.dist-info/WHEEL
passphera_core-0.34.0.dist-info/top_level.txt
passphera_core-0.34.0.dist-info/RECORD
