Metadata-Version: 2.4
Name: passphera-core
Version: 0.34.0
Summary: The core of passphera project
Home-page: https://github.com/passphera/core
Author: Fathi Abdelmalek
Author-email: passphera@imfathi.com
Classifier: Development Status :: 4 - Beta
Classifier: License :: OSI Approved :: Apache Software License
Classifier: Operating System :: OS Independent
Classifier: Programming Language :: Python
Classifier: Programming Language :: Python :: 3
Classifier: Topic :: Security
Classifier: Topic :: Security :: Cryptography
Requires-Python: >=3
License-File: LICENSE
Requires-Dist: cipherspy
Dynamic: author
Dynamic: author-email
Dynamic: classifier
Dynamic: description
Dynamic: description-content-type
Dynamic: home-page
Dynamic: license-file
Dynamic: requires-dist
Dynamic: requires-python
Dynamic: summary
